langpipe/__init__.py
langpipe/main.py
langpipe-0.0.1.dist-info/METADATA
langpipe-0.0.1.dist-info/WHEEL
langpipe-0.0.1.dist-info/top_level.txt
langpipe-0.0.1.dist-info/RECORD
