Metadata-Version: 2.1
Name: langpipe
Version: 0.0.1
Summary: LangPipe Python SDK
Home-page: https://langpipe.ai
